Metadata-Version: 2.0
Name: odoo8-addon-l10n-es
Version: 8.0.5.4.0.99.dev6
Summary: Spanish Charts of Accounts (PGCE 2008)
Home-page: https://github.com/OCA/l10n-spain
Author: Spanish Localization Team,Odoo Community Association (OCA)
Author-email: support@odoo-community.org
License: AGPL-3
Platform: UNKNOWN
Classifier: Programming Language :: Python
Classifier: Framework :: Odoo
Classifier: License :: OSI Approved :: GNU Affero General Public License v3
Requires-Python: ~=2.7
Requires-Dist: odoo (<9.0a,>=8.0a)
